{
  "users": [
    {
      "name": "Allison",
      "username": "allisoncollins",
      "password": "123",
      "id": 1
    },
    {
      "name": "Herschel",
      "username": "iamadog",
      "password": "456",
      "id": 2
    }
  ],
  "savedArt": [
    {
      "userId": "2",
      "title": "Hillsboro Village Mural",
      "rating": 0,
      "visited": false,
      "id": 24
    },
    {
      "title": "Founding Fathers Cenotaph",
      "visited": true,
      "userId": "1",
      "id": 32
    },
    {
      "userId": "1",
      "title": "Confluence",
      "rating": 0,
      "visited": false,
      "id": 36
    },
    {
      "title": "Maybelle Carter",
      "visited": true,
      "userId": "1",
      "id": 37
    },
    {
      "title": "Roy Orbison Tribute Statue",
      "visited": true,
      "userId": "1",
      "id": 38
    }
  ]
}